bw_mantis_sdk-1.2.0.dist-info/licenses/LICENSE
mantis/__init__.py
mantis/arm.py
mantis/chassis.py
mantis/constants.py
mantis/gripper.py
mantis/head.py
mantis/mantis.py
mantis/waist.py
bw_mantis_sdk-1.2.0.dist-info/METADATA
bw_mantis_sdk-1.2.0.dist-info/WHEEL
bw_mantis_sdk-1.2.0.dist-info/top_level.txt
bw_mantis_sdk-1.2.0.dist-info/RECORD
