Metadata-Version: 2.4
Name: bw-mantis-sdk
Version: 1.2.0
Summary: Mantis 机器人 Python SDK，基于 Zenoh 通信，无需安装 ROS2
Author: BlueWorm-EAI-Tech
License: MIT
Project-URL: Homepage, https://github.com/BlueWorm-EAI-Tech/mantis-sdk
Project-URL: Repository, https://github.com/BlueWorm-EAI-Tech/mantis-sdk
Keywords: robot,mantis,zenoh,ros2,sdk,sim2real
Classifier: Development Status :: 5 - Production/Stable
Classifier: Intended Audience :: Developers
Classifier: License :: OSI Approved :: MIT License
Classifier: Operating System :: OS Independent
Classifier: Programming Language :: Python :: 3
Classifier: Programming Language :: Python :: 3.8
Classifier: Programming Language :: Python :: 3.9
Classifier: Programming Language :: Python :: 3.10
Classifier: Programming Language :: Python :: 3.11
Classifier: Programming Language :: Python :: 3.12
Classifier: Topic :: Scientific/Engineering
Requires-Python: >=3.8
License-File: LICENSE
Requires-Dist: eclipse-zenoh>=1.0.0
Provides-Extra: dev
Requires-Dist: pytest; extra == "dev"
Requires-Dist: build; extra == "dev"
Requires-Dist: twine; extra == "dev"
Dynamic: license-file
